Metadata-Version: 2.1
Name: list-grouper-juanbeta
Version: 0.1
Summary: Generates a list with enumerated groups taking into account a change in consecutive values.
Home-page: https://github.com/pypa/sampleproject
Author: Juan Betancur
Author-email: juanbeta02@gmail.com
License: UNKNOWN
Platform: UNKNOWN
Classifier: Programming Language :: Python :: 3
Classifier: License :: OSI Approved :: MIT License
Classifier: Operating System :: OS Independent
Requires-Python: >=3.6
